prefect_dbt_flow/__init__.py
prefect_dbt_flow/dbt/__init__.py
prefect_dbt_flow/dbt/cli.py
prefect_dbt_flow/dbt/graph.py
prefect_dbt_flow/dbt/profile.py
prefect_dbt_flow/dbt/tasks.py
prefect_dbt_flow/flow.py
prefect_dbt_flow/py.typed
prefect_dbt_flow/utils/__init__.py
prefect_dbt_flow/utils/cmd.py
prefect_dbt_flow/version.py
prefect_dbt_flow-0.5.8.dist-info/LICENSE
prefect_dbt_flow-0.5.8.dist-info/WHEEL
prefect_dbt_flow-0.5.8.dist-info/METADATA
prefect_dbt_flow-0.5.8.dist-info/RECORD
