Metadata-Version: 2.1
Name: prefect-dbt-flow
Version: 0.5.8
Summary: Prefect - dbt integration
Home-page: https://datarootsio.github.io/prefect-dbt-flow
License: MIT
Keywords: dbt,prefect
Author: David Valdez
Author-email: david@dataroots.io
Requires-Python: >=3.9,<4.0
Classifier: License :: OSI Approved :: MIT License
Classifier: Programming Language :: Python :: 3
Classifier: Programming Language :: Python :: 3.9
Classifier: Programming Language :: Python :: 3.10
Classifier: Programming Language :: Python :: 3.11
Requires-Dist: prefect (>=2.7,<3.0)
Project-URL: Repository, https://github.com/datarootsio/prefect-dbt-flow
